fastrl2/__init__.py
fastrl2/_nbdev.py
fastrl2-2.0.19.dist-info/LICENSE
fastrl2-2.0.19.dist-info/METADATA
fastrl2-2.0.19.dist-info/WHEEL
fastrl2-2.0.19.dist-info/entry_points.txt
fastrl2-2.0.19.dist-info/top_level.txt
fastrl2-2.0.19.dist-info/RECORD
