Metadata-Version: 2.1
Name: fastrl2
Version: 2.0.19
Summary: fastrl is a reinforcement learning library that extends Fastai. This project is not affiliated with fastai or Jeremy Howard.
Home-page: https://github.com/josiahls/fastrl2/tree/master/
Author: Josiah Laivins, and contributors
Author-email: 
License: Apache Software License 2.0
Keywords: fastrl,reinforcement learning,rl,robotics,fastai,deep learning,machine learning,
Platform: UNKNOWN
Classifier: Development Status :: 4 - Beta
Classifier: Intended Audience :: Developers
Classifier: License :: OSI Approved :: Apache Software License
Classifier: Natural Language :: English
Classifier: Programming Language :: Python :: 3.6
Classifier: Programming Language :: Python :: 3.7
Classifier: Programming Language :: Python :: 3.8
Requires-Python: >=3.6
Requires-Dist: fastai (>=2.0.0)
